{
    "local_variable": {
        "1213710338": {
            "variable_dict": {
                "PROJECTILE_ENTITY": {
                    "\u6295\u5c04\u7269": 0
                }, 
                "UNIT_ENTITY": {
                    "\u76ee\u6807\u5355\u4f4d": 0
                }
            }, 
            "variable_length_dict": {
                "\u6295\u5c04\u7269": 0, 
                "\u76ee\u6807\u5355\u4f4d": 0
            }
        }, 
        "2051366913": {
            "variable_dict": {
                "PROJECTILE_ENTITY": {
                    "\u6295\u5c04\u7269": 0
                }, 
                "UNIT_ENTITY": {
                    "\u76ee\u6807\u5355\u4f4d": 0
                }
            }, 
            "variable_length_dict": {
                "\u6295\u5c04\u7269": 0, 
                "\u76ee\u6807\u5355\u4f4d": 0
            }
        }
    }, 
    "trigger_dict": {
        "1213710338": {
            "action": [
                {
                    "action_type": "SET_VARIABLE", 
                    "args_list": [
                        {
                            "arg_type": 100030, 
                            "args_list": [
                                [
                                    "ANGLE", 
                                    "\u65bd\u6cd5\u65b9\u5411", 
                                    "actor"
                                ]
                            ], 
                            "sub_type": 1
                        }, 
                        {
                            "arg_type": 100225, 
                            "args_list": [
                                {
                                    "arg_type": 100014, 
                                    "args_list": [], 
                                    "sub_type": "CUR_ABILITY"
                                }
                            ], 
                            "sub_type": "GET_ABILITY_RELEASE_DIRECTION"
                        }
                    ], 
                    "bp": false, 
                    "element_id": 2051366913000017, 
                    "enable": true
                }, 
                {
                    "action_type": "SET_VARIABLE", 
                    "args_list": [
                        {
                            "arg_type": 100030, 
                            "args_list": [
                                [
                                    "PROJECTILE_ENTITY", 
                                    "\u6295\u5c04\u7269", 
                                    "actor"
                                ]
                            ], 
                            "sub_type": 1
                        }, 
                        {
                            "arg_type": 100077, 
                            "args_list": [
                                {
                                    "arg_type": 100062, 
                                    "args_list": [
                                        134234480
                                    ], 
                                    "sub_type": 1
                                }, 
                                {
                                    "arg_type": 100004, 
                                    "args_list": [
                                        {
                                            "arg_type": 100006, 
                                            "args_list": [], 
                                            "sub_type": "ABILITY_OWNER"
                                        }
                                    ], 
                                    "sub_type": "UNIT_ENTITY_POINT"
                                }, 
                                {
                                    "arg_type": 100006, 
                                    "args_list": [], 
                                    "sub_type": "ABILITY_OWNER"
                                }
                            ], 
                            "op_arg": [
                                {
                                    "arg_type": 100225, 
                                    "args_list": [
                                        [
                                            "ANGLE", 
                                            "\u65bd\u6cd5\u65b9\u5411", 
                                            "actor"
                                        ]
                                    ], 
                                    "sub_type": 2
                                }, 
                                {
                                    "arg_type": 100014, 
                                    "args_list": [], 
                                    "sub_type": "CUR_ABILITY"
                                }, 
                                {
                                    "arg_type": 100000, 
                                    "args_list": [
                                        2.0
                                    ], 
                                    "sub_type": 1
                                }, 
                                {
                                    "arg_type": 100000, 
                                    "args_list": [
                                        150.0
                                    ], 
                                    "sub_type": 1
                                }, 
                                null, 
                                {
                                    "arg_type": 100001, 
                                    "args_list": [
                                        true
                                    ], 
                                    "sub_type": 1
                                }, 
                                null
                            ], 
                            "op_arg_enable": [
                                true, 
                                true, 
                                true, 
                                true, 
                                false, 
                                false, 
                                false
                            ], 
                            "sub_type": "CREATE_PROJECTILE_NEW"
                        }
                    ], 
                    "bp": false, 
                    "element_id": 2051366913000013, 
                    "enable": true
                }, 
                {
                    "action_type": "CREATE_STRAIGHT_MOVER_SAVE", 
                    "args_list": [
                        {
                            "arg_type": 100263, 
                            "args_list": [
                                [
                                    "MOVER_ENTITY", 
                                    "\u8fd0\u52a8\u5668", 
                                    "actor"
                                ]
                            ], 
                            "sub_type": 6
                        }, 
                        {
                            "arg_type": 100077, 
                            "args_list": [
                                [
                                    "PROJECTILE_ENTITY", 
                                    "\u6295\u5c04\u7269", 
                                    "actor"
                                ]
                            ], 
                            "sub_type": "VARIABLE"
                        }, 
                        {
                            "arg_type": 100225, 
                            "args_list": [
                                [
                                    "ANGLE", 
                                    "\u65bd\u6cd5\u65b9\u5411", 
                                    "actor"
                                ]
                            ], 
                            "sub_type": 2
                        }, 
                        {
                            "arg_type": 100000, 
                            "args_list": [
                                {
                                    "arg_type": 100014, 
                                    "args_list": [], 
                                    "sub_type": "CUR_ABILITY"
                                }, 
                                {
                                    "arg_type": 100078, 
                                    "args_list": [
                                        "ability_cast_range"
                                    ], 
                                    "sub_type": 1
                                }
                            ], 
                            "sub_type": "GET_ABILITY_FLOAT_ATTR"
                        }, 
                        {
                            "arg_type": 100000, 
                            "args_list": [
                                2000.0
                            ], 
                            "sub_type": 1
                        }, 
                        {
                            "arg_type": 100000, 
                            "args_list": [
                                0.0
                            ], 
                            "sub_type": 1
                        }, 
                        {
                            "arg_type": 100022, 
                            "args_list": [], 
                            "sub_type": 1
                        }, 
                        {
                            "arg_type": 100022, 
                            "args_list": [], 
                            "sub_type": 1
                        }, 
                        {
                            "arg_type": 100022, 
                            "args_list": [
                                {
                                    "action_type": "PROJECTILE_DELETE", 
                                    "args_list": [
                                        {
                                            "arg_type": 100077, 
                                            "args_list": [
                                                [
                                                    "PROJECTILE_ENTITY", 
                                                    "\u6295\u5c04\u7269", 
                                                    "actor"
                                                ]
                                            ], 
                                            "sub_type": "VARIABLE"
                                        }
                                    ], 
                                    "bp": false, 
                                    "element_id": 1213710338970112, 
                                    "enable": true, 
                                    "op_arg": [
                                        {
                                            "arg_type": 100001, 
                                            "args_list": [
                                                true
                                            ], 
                                            "sub_type": 1
                                        }
                                    ], 
                                    "op_arg_enable": [
                                        true
                                    ]
                                }
                            ], 
                            "sub_type": 1
                        }, 
                        {
                            "arg_type": 100022, 
                            "args_list": [], 
                            "sub_type": 1
                        }, 
                        {
                            "arg_type": 100022, 
                            "args_list": [
                                {
                                    "action_type": "IF_THEN_ELSE", 
                                    "args_list": [
                                        {
                                            "arg_type": 100021, 
                                            "args_list": [
                                                {
                                                    "args_list": [
                                                        {
                                                            "arg_type": 100010, 
                                                            "args_list": [
                                                                {
                                                                    "arg_type": 100006, 
                                                                    "args_list": [], 
                                                                    "sub_type": "MOVER_COLLIDE_UNIT"
                                                                }
                                                            ], 
                                                            "sub_type": "GET_UNIT_TYPE"
                                                        }, 
                                                        {
                                                            "arg_type": 100035, 
                                                            "args_list": [
                                                                "!="
                                                            ], 
                                                            "sub_type": 1
                                                        }, 
                                                        {
                                                            "arg_type": 100010, 
                                                            "args_list": [
                                                                2
                                                            ], 
                                                            "sub_type": 1
                                                        }
                                                    ], 
                                                    "condition_type": "UNIT_TYPE_COMPARE", 
                                                    "element_id": 2051366913000148, 
                                                    "enable": true
                                                }
                                            ], 
                                            "sub_type": 1
                                        }, 
                                        {
                                            "arg_type": 100022, 
                                            "args_list": [
                                                {
                                                    "action_type": "SET_VARIABLE", 
                                                    "args_list": [
                                                        {
                                                            "arg_type": 100000, 
                                                            "args_list": [
                                                                [
                                                                    "FLOAT", 
                                                                    "\u4f24\u5bb3", 
                                                                    "actor"
                                                                ]
                                                            ], 
                                                            "sub_type": 2
                                                        }, 
                                                        {
                                                            "arg_type": 100000, 
                                                            "args_list": [
                                                                {
                                                                    "arg_type": 100014, 
                                                                    "args_list": [], 
                                                                    "sub_type": "CUR_ABILITY"
                                                                }, 
                                                                {
                                                                    "arg_type": 100003, 
                                                                    "args_list": [
                                                                        "\u4f24\u5bb3"
                                                                    ], 
                                                                    "sub_type": 1
                                                                }
                                                            ], 
                                                            "sub_type": "GET_FLOAT_KV"
                                                        }
                                                    ], 
                                                    "bp": false, 
                                                    "element_id": 1894567937000089, 
                                                    "enable": true
                                                }, 
                                                {
                                                    "action_type": "BREAK_MOVER", 
                                                    "args_list": [
                                                        {
                                                            "arg_type": 100263, 
                                                            "args_list": [
                                                                [
                                                                    "MOVER_ENTITY", 
                                                                    "\u8fd0\u52a8\u5668", 
                                                                    "actor"
                                                                ]
                                                            ], 
                                                            "sub_type": 6
                                                        }
                                                    ], 
                                                    "bp": false, 
                                                    "element_id": 2051366913860061, 
                                                    "enable": true
                                                }, 
                                                {
                                                    "action_type": "PROJECTILE_DELETE", 
                                                    "args_list": [
                                                        {
                                                            "arg_type": 100077, 
                                                            "args_list": [
                                                                [
                                                                    "PROJECTILE_ENTITY", 
                                                                    "\u6295\u5c04\u7269", 
                                                                    "actor"
                                                                ]
                                                            ], 
                                                            "sub_type": "VARIABLE"
                                                        }
                                                    ], 
                                                    "bp": false, 
                                                    "element_id": 2051366913000047, 
                                                    "enable": true, 
                                                    "op_arg": [
                                                        {
                                                            "arg_type": 100001, 
                                                            "args_list": [
                                                                true
                                                            ], 
                                                            "sub_type": 1
                                                        }
                                                    ], 
                                                    "op_arg_enable": [
                                                        true
                                                    ]
                                                }, 
                                                {
                                                    "action_type": "ADD_ATTR", 
                                                    "args_list": [
                                                        {
                                                            "arg_type": 100006, 
                                                            "args_list": [], 
                                                            "sub_type": "ABILITY_OWNER"
                                                        }, 
                                                        {
                                                            "arg_type": 100300, 
                                                            "args_list": [
                                                                "ATTR_ALL_RATIO"
                                                            ], 
                                                            "sub_type": 1
                                                        }, 
                                                        {
                                                            "arg_type": 100042, 
                                                            "args_list": [
                                                                "critical_chance"
                                                            ], 
                                                            "sub_type": 1
                                                        }, 
                                                        {
                                                            "arg_type": 100000, 
                                                            "args_list": [
                                                                -100.0
                                                            ], 
                                                            "sub_type": 1
                                                        }
                                                    ], 
                                                    "bp": false, 
                                                    "element_id": 1644036097970412, 
                                                    "enable": true
                                                }, 
                                                {
                                                    "action_type": "APPLY_DAMAGE", 
                                                    "args_list": [
                                                        {
                                                            "arg_type": 100006, 
                                                            "args_list": [], 
                                                            "sub_type": "ABILITY_OWNER"
                                                        }, 
                                                        {
                                                            "arg_type": 100014, 
                                                            "args_list": [], 
                                                            "sub_type": "CUR_ABILITY"
                                                        }, 
                                                        {
                                                            "arg_type": 100006, 
                                                            "args_list": [], 
                                                            "sub_type": "MOVER_COLLIDE_UNIT"
                                                        }, 
                                                        {
                                                            "arg_type": 100064, 
                                                            "args_list": [
                                                                0
                                                            ], 
                                                            "sub_type": 1
                                                        }, 
                                                        {
                                                            "arg_type": 100000, 
                                                            "args_list": [
                                                                [
                                                                    "FLOAT", 
                                                                    "\u4f24\u5bb3", 
                                                                    "actor"
                                                                ]
                                                            ], 
                                                            "sub_type": 2
                                                        }, 
                                                        {
                                                            "arg_type": 100001, 
                                                            "args_list": [
                                                                true
                                                            ], 
                                                            "sub_type": 1
                                                        }
                                                    ], 
                                                    "bp": false, 
                                                    "element_id": 2043138049000045, 
                                                    "enable": true, 
                                                    "op_arg": [
                                                        {
                                                            "arg_type": 100001, 
                                                            "args_list": [
                                                                true
                                                            ], 
                                                            "sub_type": 1
                                                        }, 
                                                        {
                                                            "arg_type": 100001, 
                                                            "args_list": [
                                                                true
                                                            ], 
                                                            "sub_type": 1
                                                        }, 
                                                        {
                                                            "arg_type": 100001, 
                                                            "args_list": [
                                                                true
                                                            ], 
                                                            "sub_type": 1
                                                        }, 
                                                        null, 
                                                        null, 
                                                        null, 
                                                        null, 
                                                        null, 
                                                        null
                                                    ], 
                                                    "op_arg_enable": [
                                                        true, 
                                                        false, 
                                                        false, 
                                                        false, 
                                                        false, 
                                                        false, 
                                                        false, 
                                                        false, 
                                                        false
                                                    ]
                                                }, 
                                                {
                                                    "action_type": "ADD_ATTR", 
                                                    "args_list": [
                                                        {
                                                            "arg_type": 100006, 
                                                            "args_list": [], 
                                                            "sub_type": "ABILITY_OWNER"
                                                        }, 
                                                        {
                                                            "arg_type": 100300, 
                                                            "args_list": [
                                                                "ATTR_ALL_RATIO"
                                                            ], 
                                                            "sub_type": 1
                                                        }, 
                                                        {
                                                            "arg_type": 100042, 
                                                            "args_list": [
                                                                "critical_chance"
                                                            ], 
                                                            "sub_type": 1
                                                        }, 
                                                        {
                                                            "arg_type": 100000, 
                                                            "args_list": [
                                                                100.0
                                                            ], 
                                                            "sub_type": 1
                                                        }
                                                    ], 
                                                    "bp": false, 
                                                    "element_id": 1644036097970072, 
                                                    "enable": true
                                                }, 
                                                {
                                                    "action_type": "CREATE_SFX_ON_UNIT", 
                                                    "args_list": [
                                                        {
                                                            "arg_type": 100066, 
                                                            "args_list": [
                                                                104995
                                                            ], 
                                                            "sub_type": 1
                                                        }, 
                                                        {
                                                            "arg_type": 100006, 
                                                            "args_list": [], 
                                                            "sub_type": "MOVER_COLLIDE_UNIT"
                                                        }, 
                                                        {
                                                            "arg_type": 100003, 
                                                            "args_list": [
                                                                "hit_point"
                                                            ], 
                                                            "sub_type": 1
                                                        }, 
                                                        {
                                                            "arg_type": 100001, 
                                                            "args_list": [
                                                                false
                                                            ], 
                                                            "sub_type": 1
                                                        }, 
                                                        {
                                                            "arg_type": 100001, 
                                                            "args_list": [
                                                                true
                                                            ], 
                                                            "sub_type": 1
                                                        }
                                                    ], 
                                                    "bp": false, 
                                                    "element_id": 16440360970005, 
                                                    "enable": true, 
                                                    "op_arg": [
                                                        null, 
                                                        {
                                                            "arg_type": 100000, 
                                                            "args_list": [
                                                                1.0
                                                            ], 
                                                            "sub_type": 1
                                                        }, 
                                                        null, 
                                                        null
                                                    ], 
                                                    "op_arg_enable": [
                                                        false, 
                                                        true, 
                                                        false, 
                                                        false
                                                    ]
                                                }, 
                                                [
                                                    1261912008, 
                                                    "\u51fb\u4e2d\u89e6\u53d1\u6548\u679c", 
                                                    1213710338, 
                                                    "action_type"
                                                ], 
                                                {
                                                    "action_type": "ADD_MODIFIER", 
                                                    "args_list": [
                                                        {
                                                            "arg_type": 100006, 
                                                            "args_list": [], 
                                                            "sub_type": "ABILITY_OWNER"
                                                        }, 
                                                        {
                                                            "arg_type": 100046, 
                                                            "args_list": [
                                                                134250441
                                                            ], 
                                                            "sub_type": 1
                                                        }
                                                    ], 
                                                    "bp": false, 
                                                    "element_id": 2123456515000007, 
                                                    "enable": true, 
                                                    "op_arg": [
                                                        {
                                                            "arg_type": 100006, 
                                                            "args_list": [], 
                                                            "sub_type": "ABILITY_OWNER"
                                                        }, 
                                                        {
                                                            "arg_type": 100014, 
                                                            "args_list": [], 
                                                            "sub_type": "CUR_ABILITY"
                                                        }, 
                                                        {
                                                            "arg_type": 100000, 
                                                            "args_list": [
                                                                6.0
                                                            ], 
                                                            "sub_type": 1
                                                        }, 
                                                        null, 
                                                        {
                                                            "arg_type": 100002, 
                                                            "args_list": [
                                                                {
                                                                    "arg_type": 100000, 
                                                                    "args_list": [
                                                                        {
                                                                            "arg_type": 100014, 
                                                                            "args_list": [], 
                                                                            "sub_type": "CUR_ABILITY"
                                                                        }, 
                                                                        {
                                                                            "arg_type": 100003, 
                                                                            "args_list": [
                                                                                "\u79fb\u901f"
                                                                            ], 
                                                                            "sub_type": 1
                                                                        }
                                                                    ], 
                                                                    "sub_type": "GET_FLOAT_KV"
                                                                }
                                                            ], 
                                                            "sub_type": "F2I"
                                                        }, 
                                                        null
                                                    ], 
                                                    "op_arg_enable": [
                                                        true, 
                                                        true, 
                                                        true, 
                                                        false, 
                                                        false, 
                                                        false
                                                    ]
                                                }, 
                                                {
                                                    "action_type": "ITER_ABILITY_DO", 
                                                    "args_list": [
                                                        {
                                                            "arg_type": 100006, 
                                                            "args_list": [], 
                                                            "sub_type": "ABILITY_OWNER"
                                                        }, 
                                                        {
                                                            "arg_type": 100182, 
                                                            "args_list": [
                                                                3
                                                            ], 
                                                            "sub_type": 1
                                                        }, 
                                                        {
                                                            "arg_type": 100022, 
                                                            "args_list": [
                                                                {
                                                                    "action_type": "ADD_ABILITY_CD", 
                                                                    "args_list": [
                                                                        {
                                                                            "arg_type": 100014, 
                                                                            "args_list": [], 
                                                                            "sub_type": "FOR_EACH_SELECTED_ABILITY"
                                                                        }, 
                                                                        {
                                                                            "arg_type": 100000, 
                                                                            "args_list": [
                                                                                -1.5
                                                                            ], 
                                                                            "sub_type": 1
                                                                        }
                                                                    ], 
                                                                    "bp": false, 
                                                                    "element_id": 1213710338970131, 
                                                                    "enable": true
                                                                }
                                                            ], 
                                                            "sub_type": 1
                                                        }
                                                    ], 
                                                    "bp": false, 
                                                    "element_id": 1213710338970115, 
                                                    "enable": true
                                                }
                                            ], 
                                            "sub_type": 1
                                        }, 
                                        {
                                            "arg_type": 100022, 
                                            "args_list": [], 
                                            "sub_type": 1
                                        }
                                    ], 
                                    "bp": false, 
                                    "element_id": 2051366913000131, 
                                    "enable": true, 
                                    "fake_op": [
                                        2
                                    ]
                                }
                            ], 
                            "sub_type": 1
                        }
                    ], 
                    "bp": false, 
                    "element_id": 2051366913000022, 
                    "enable": true, 
                    "fake_op": [
                        8, 
                        10
                    ], 
                    "local_var": {
                        "__tuple__": true, 
                        "items": [
                            {}, 
                            {}
                        ]
                    }, 
                    "op_arg": [
                        null, 
                        null, 
                        null, 
                        null, 
                        null, 
                        {
                            "arg_type": 100176, 
                            "args_list": [
                                0
                            ], 
                            "sub_type": 1
                        }, 
                        {
                            "arg_type": 100000, 
                            "args_list": [
                                120.0
                            ], 
                            "sub_type": 1
                        }, 
                        {
                            "arg_type": 100001, 
                            "args_list": [
                                true
                            ], 
                            "sub_type": 1
                        }, 
                        {
                            "arg_type": 100001, 
                            "args_list": [
                                true
                            ], 
                            "sub_type": 1
                        }, 
                        {
                            "arg_type": 100001, 
                            "args_list": [
                                true
                            ], 
                            "sub_type": 1
                        }, 
                        null, 
                        {
                            "arg_type": 100001, 
                            "args_list": [
                                true
                            ], 
                            "sub_type": 1
                        }, 
                        null, 
                        {
                            "arg_type": 100006, 
                            "args_list": [], 
                            "sub_type": "ABILITY_OWNER"
                        }, 
                        {
                            "arg_type": 100014, 
                            "args_list": [], 
                            "sub_type": "CUR_ABILITY"
                        }, 
                        null, 
                        null
                    ], 
                    "op_arg_enable": [
                        false, 
                        false, 
                        false, 
                        false, 
                        false, 
                        true, 
                        true, 
                        false, 
                        false, 
                        false, 
                        false, 
                        false, 
                        false, 
                        true, 
                        true, 
                        false, 
                        false
                    ]
                }
            ], 
            "call_enabled": true, 
            "condition": [], 
            "enabled": true, 
            "event": [
                {
                    "args_list": [], 
                    "element_id": 1213710338000002, 
                    "enable": true, 
                    "event_type": "ABILITY_SP_END"
                }
            ], 
            "group_id": 134269539, 
            "p_trigger_id": null, 
            "trigger_id": 1213710338, 
            "trigger_name": "\u65b0\u5efa\u89e6\u53d1\u5668_2", 
            "valid": true, 
            "var_data": [
                {
                    "PROJECTILE_ENTITY": {
                        "\u6295\u5c04\u7269": 0
                    }, 
                    "UNIT_ENTITY": {
                        "\u76ee\u6807\u5355\u4f4d": 0
                    }
                }, 
                {
                    "\u6295\u5c04\u7269": 0, 
                    "\u76ee\u6807\u5355\u4f4d": 0
                }, 
                [
                    "\u6295\u5c04\u7269", 
                    "\u76ee\u6807\u5355\u4f4d"
                ]
            ]
        }, 
        "2051366913": {
            "action": [
                {
                    "action_type": "PLAY_ANIMATION", 
                    "args_list": [
                        {
                            "arg_type": 100006, 
                            "args_list": [], 
                            "sub_type": "ABILITY_OWNER"
                        }, 
                        {
                            "arg_type": 100003, 
                            "args_list": [
                                "attack1"
                            ], 
                            "sub_type": 1
                        }, 
                        {
                            "arg_type": 100000, 
                            "args_list": [
                                1.0
                            ], 
                            "sub_type": 1
                        }, 
                        {
                            "arg_type": 100000, 
                            "args_list": [
                                0.0
                            ], 
                            "sub_type": 1
                        }, 
                        {
                            "arg_type": 100000, 
                            "args_list": [
                                -1.0
                            ], 
                            "sub_type": 1
                        }, 
                        {
                            "arg_type": 100001, 
                            "args_list": [
                                false
                            ], 
                            "sub_type": 1
                        }, 
                        {
                            "arg_type": 100001, 
                            "args_list": [
                                true
                            ], 
                            "sub_type": 1
                        }
                    ], 
                    "bp": false, 
                    "element_id": 2043138049860046, 
                    "enable": true, 
                    "op_arg": [
                        {
                            "arg_type": 100000, 
                            "args_list": [
                                -1.0
                            ], 
                            "sub_type": 1
                        }, 
                        {
                            "arg_type": 100001, 
                            "args_list": [
                                false
                            ], 
                            "sub_type": 1
                        }
                    ], 
                    "op_arg_enable": [
                        false, 
                        false
                    ]
                }
            ], 
            "call_enabled": true, 
            "condition": [], 
            "enabled": true, 
            "event": [
                {
                    "args_list": [], 
                    "element_id": 2051366913000003, 
                    "enable": true, 
                    "event_type": "ABILITY_PS_START"
                }
            ], 
            "group_id": 134269539, 
            "p_trigger_id": null, 
            "trigger_id": 2051366913, 
            "trigger_name": "\u65b0\u5efa\u89e6\u53d1\u5668", 
            "valid": true, 
            "var_data": [
                {
                    "PROJECTILE_ENTITY": {
                        "\u6295\u5c04\u7269": 0
                    }, 
                    "UNIT_ENTITY": {
                        "\u76ee\u6807\u5355\u4f4d": 0
                    }
                }, 
                {
                    "\u6295\u5c04\u7269": 0, 
                    "\u76ee\u6807\u5355\u4f4d": 0
                }, 
                [
                    "\u6295\u5c04\u7269", 
                    "\u76ee\u6807\u5355\u4f4d"
                ]
            ]
        }
    }, 
    "trigger_group_info": [
        {
            "_trigger_group_": true, 
            "group": [
                {
                    "__tuple__": true, 
                    "items": [
                        2051366913, 
                        "\u65b0\u5efa\u89e6\u53d1\u5668"
                    ]
                }, 
                {
                    "__tuple__": true, 
                    "items": [
                        1213710338, 
                        "\u65b0\u5efa\u89e6\u53d1\u5668_2"
                    ]
                }
            ], 
            "key": 134269539, 
            "name": "134269539"
        }
    ], 
    "trigger_version": "1.2", 
    "variable_dict": {
        "ABILITY": {}, 
        "ANGLE": {
            "\u65bd\u6cd5\u65b9\u5411": 0.0
        }, 
        "FLOAT": {
            "\u4f24\u5bb3": 0.0, 
            "\u63a7\u5236\u65f6\u95f4": 0.0
        }, 
        "LINK_SFX_ENTITY": {}, 
        "MODIFIER_ENTITY": {}, 
        "MOVER_ENTITY": {
            "\u8fd0\u52a8\u5668": 0
        }, 
        "POINT": {}, 
        "PROJECTILE_ENTITY": {
            "\u6295\u5c04\u7269": 0
        }, 
        "UNIT_ENTITY": {}
    }, 
    "variable_group_info": [
        {
            "__tuple__": true, 
            "items": [
                "\u65bd\u6cd5\u65b9\u5411", 
                "\u65bd\u6cd5\u65b9\u5411"
            ]
        }, 
        {
            "__tuple__": true, 
            "items": [
                "\u6295\u5c04\u7269", 
                "\u6295\u5c04\u7269"
            ]
        }, 
        {
            "__tuple__": true, 
            "items": [
                "\u4f24\u5bb3", 
                "\u4f24\u5bb3"
            ]
        }, 
        {
            "__tuple__": true, 
            "items": [
                "\u63a7\u5236\u65f6\u95f4", 
                "\u63a7\u5236\u65f6\u95f4"
            ]
        }, 
        {
            "__tuple__": true, 
            "items": [
                "\u8fd0\u52a8\u5668", 
                "\u8fd0\u52a8\u5668"
            ]
        }
    ], 
    "variable_length_dict": {
        "\u4f24\u5bb3": 0, 
        "\u6295\u5c04\u7269": 0, 
        "\u63a7\u5236\u65f6\u95f4": 0, 
        "\u65bd\u6cd5\u65b9\u5411": 0, 
        "\u8fd0\u52a8\u5668": 0
    }
}