[
    {
        "type": "ability",
        "name": "敏捷",
        "id": 201385537,
        "icon": 106724,
        "description": "当前：敏捷 +100，木材 +50。\n后继：猎魔人。"
    },
    {
        "type": "ability",
        "name": "猎魔人",
        "id": 201385538,
        "icon": 108140,
        "description": "当前：攻击范围 +100，敏捷 +120。每进化 1 次，敏捷增幅 +2%，每秒敏捷 +0.2，物理伤害 +3%。\n后继：弓神。"
    },
    {
        "type": "ability",
        "name": "弓神",
        "id": 201385539,
        "icon": 108148,
        "description": "当前：命中 +20%，攻击范围 +150，普攻伤害 +15%，多重数量 +1，弹射次数 +1。\n最终敏捷 +5%，每点敏捷额外提供 0.1 攻击力。"
    },
    {
        "type": "ability",
        "name": "力量",
        "id": 201385540,
        "icon": 106775,
        "description": "当前：力量 +100，木材 +50。\n后继：野蛮人。"
    },
    {
        "type": "ability",
        "name": "野蛮人",
        "id": 201385541,
        "icon": 106751,
        "description": "当前：每次击杀永久攻击 +2。\n后继：战神。"
    },
    {
        "type": "ability",
        "name": "战神",
        "id": 201385542,
        "icon": 107026,
        "description": "当前：力量 +200，力量增幅 +10%，物理暴击 +10%，生命值 +800，护甲 +10，格挡 +5。\n最终力量 +5%，每点力量额外提供 0.1 攻击力。"
    },
    {
        "type": "ability",
        "name": "智力",
        "id": 201385543,
        "icon": 106912,
        "description": "当前：智力 +100，木材 +50。\n后继：秘法师。"
    },
    {
        "type": "ability",
        "name": "秘法师",
        "id": 201385544,
        "icon": 106905,
        "description": "当前：魔法暴击 +3%，魔法暴伤 +9%，技能急速 +15。每进化 1 次，智力增幅 +2%，每秒智力 +0.2，魔法伤害 +3%。\n后继：法神。"
    },
    {
        "type": "ability",
        "name": "法神",
        "id": 201385545,
        "icon": 106916,
        "description": "当前：智力 +100，全系伤害 +15%，每拥有 1 个初始技能，智力增幅 +4%。\n最终智力 +5%，每点智力额外提供 0.1 攻击力。"
    },
    {
        "type": "ability",
        "name": "致命",
        "id": 201385546,
        "icon": 106810,
        "description": "当前：物理暴击 +3%，魔法暴击 +3%。非暴击伤害 -20%，暴击伤害 +20%。\n后继：大炮。"
    },
    {
        "type": "ability",
        "name": "大炮",
        "id": 201385547,
        "icon": 106686,
        "description": "当前：致命攻击 / 致命魔法：物理或魔法暴击 +5%，暴击伤害 20% 概率翻倍。\n致命攻击：每溢出 2% 物理暴击，致命攻击触发概率 +1%。致命魔法：溢出 1% 魔法暴击，转化为 2% 魔法暴伤。"
    },
    {
        "type": "ability",
        "name": "广射",
        "id": 201385548,
        "icon": 106785,
        "description": "当前：攻击范围 +150。每100攻击范围提高 1% 普攻伤害。\n后继：月刃。"
    },
    {
        "type": "ability",
        "name": "月刃",
        "id": 201385549,
        "icon": 108246,
        "description": "当前：弹射次数 +1，弹射伤害 +15%。\n立即获得当前弹射次数 * 50 敏捷，弹射伤害 > 100% 时每溢出 1% 转化为 1% 普攻伤害。"
    },
    {
        "type": "ability",
        "name": "速攻",
        "id": 201385550,
        "icon": 106700,
        "description": "当前：攻速 +30%，攻击间隔 -0.1。\n攻击 20% 概率提升 100% 攻速，持续 5 秒。"
    },
    {
        "type": "ability",
        "name": "射术",
        "id": 201385551,
        "icon": 107004,
        "description": "当前：攻击力 +50，敏捷 +50。穿云箭：每攻击 15 次射出 1 支，造成 300% 敏捷伤害。\n后继：多重箭。"
    },
    {
        "type": "ability",
        "name": "多重箭",
        "id": 201385552,
        "icon": 106787,
        "description": "当前：多重数量 +1，多重伤害 +15%。\n立即获得当前多重数量 * 50 敏捷，多重伤害 > 100% 时每溢出 1% 转化为 1% 普攻伤害。"
    },
    {
        "type": "ability",
        "name": "魔法师",
        "id": 201385553,
        "icon": 107016,
        "description": "当前：技能伤害 +5%，魔法伤害 +7.5%。魔爆术：每18秒触发，对300范围造成200%智力伤害。"
    },
    {
        "type": "ability",
        "name": "魔能",
        "id": 201385554,
        "icon": 107049,
        "description": "当前：技能急速 +10。溢出 2 点急速提升 1% 技能伤害。"
    },
    {
        "type": "ability",
        "name": "魔术",
        "id": 201385555,
        "icon": 107051,
        "description": "当前：魔爆术范围 +150，魔爆术冷却 -5 秒。\n每拥有 1 个初始技能，魔爆触发次数 +1。"
    },
    {
        "type": "ability",
        "name": "急速",
        "id": 201385556,
        "icon": 106857,
        "description": "当前：技能急速 +10，魔法伤害 +5%，智力 +111。\n技能冷却时 7% 概率立即重置冷却。"
    },
    {
        "type": "ability",
        "name": "元素师",
        "id": 201385557,
        "icon": 106858,
        "description": "当前：魔法伤害 +5%，元素伤害 +10%。\n造成物系 / 电系 / 风系伤害时，受另外 2 种 15% 增幅。"
    },
    {
        "type": "ability",
        "name": "贪婪",
        "id": 201385558,
        "icon": 106694,
        "description": "当前：以击杀金币收益为主，承接贪欲金币 / 贪欲之刃 / 贪欲钥匙。\n随机吞噬 4 张可吞噬卡牌。"
    },
    {
        "type": "ability",
        "name": "挑战",
        "id": 201385559,
        "icon": 107382,
        "description": "当前：杀敌经验 +10%，杀敌加成 +10%。\n每秒木材 +0.4，每秒金币 +10。"
    },
    {
        "type": "ability",
        "name": "生命",
        "id": 201385560,
        "icon": 107362,
        "description": "当前：生命值 +200，生命增幅 +5%，护甲 +5。\n后继：血誓 / 血魔。"
    },
    {
        "type": "ability",
        "name": "血誓",
        "id": 201385561,
        "icon": 106542,
        "description": "当前：生命值 +500。每100点生命上限转为额外属性：血刃 / 血契 / 血矛效果翻倍。"
    },
    {
        "type": "ability",
        "name": "血魔",
        "id": 201385562,
        "icon": 106720,
        "description": "当前：攻击力 +100，力量 +100。每损失 1% 最大生命，所有伤害 +0.5%。\n每损失 35% 最大生命值触发回血，造成 50% 生命伤害并晕眩。"
    },
    {
        "type": "ability",
        "name": "战术",
        "id": 201385563,
        "icon": 106761,
        "description": "当前：斗气场域内敌人护甲 -10%，攻击力 -30%。\n斗气场域额外附加 30% 生命伤害，每击杀 1 敌力量 +0.5。"
    },
    {
        "type": "ability",
        "name": "固守",
        "id": 201385564,
        "icon": 106869,
        "description": "当前：生命值 +100，护甲 +5，格挡 +5。\n护甲增幅 +10%，单次伤害不超过最大生命值 35%。后继：陷阵。"
    },
    {
        "type": "ability",
        "name": "陷阵",
        "id": 201385565,
        "icon": 106989,
        "description": "当前：护甲 +5，格挡 +5；每击杀100敌伤害减免 +1%，最高25%。\n每击杀200敌触发全属性 +20%、攻速 +50%、技能急速 +30，持续10秒。"
    }
]
